promptlayer/__init__.py
promptlayer/promptlayer.py
promptlayer/utils.py
promptlayer/langchain/__init__.py
promptlayer/langchain/llms/__init__.py
promptlayer/langchain/llms/openai.py
tester_sc_pr2-0.1.64.dist-info/LICENSE
tester_sc_pr2-0.1.64.dist-info/METADATA
tester_sc_pr2-0.1.64.dist-info/WHEEL
tester_sc_pr2-0.1.64.dist-info/top_level.txt
tester_sc_pr2-0.1.64.dist-info/RECORD
