Metadata-Version: 2.1
Name: tester-sc-pr2
Version: 0.1.64
Summary: package to keep track of your GPT models training
License-File: LICENSE
Requires-Dist: requests
Requires-Dist: openai
Requires-Dist: langchain
